pypescript/__init__.py
pypescript-0.0.2.dist-info/LICENSE
pypescript-0.0.2.dist-info/METADATA
pypescript-0.0.2.dist-info/WHEEL
pypescript-0.0.2.dist-info/top_level.txt
pypescript-0.0.2.dist-info/RECORD
