Metadata-Version: 2.1
Name: pypescript
Version: 0.0.2
Summary: todo later
Author-email: Nguyen Thanh Nghi <thanhnghic4@gmail.com>
Project-URL: Homepage, https://github.com/thanhnghic4/Pypescript/tree/master
Project-URL: Bug Tracker, https://github.com/thanhnghic4/Pypescript/issues
Classifier: Programming Language :: Python :: 3
Classifier: License :: OSI Approved :: MIT License
Classifier: Operating System :: OS Independent
Requires-Python: >=3.9
License-File: LICENSE
